geneweaver/tools/boolean_algebra/__init__.py
geneweaver/tools/boolean_algebra/intersection.py
geneweaver/tools/boolean_algebra/plugin.py
geneweaver/tools/boolean_algebra/schema.py
geneweaver/tools/boolean_algebra/symmetric_difference.py
geneweaver/tools/boolean_algebra/tool.py
geneweaver/tools/boolean_algebra/union.py
geneweaver/tools/boolean_algebra/utils.py
geneweaver/tools/boolean_algebra/workflow/boolean_algebra.nf
geneweaver_boolean_algebra-0.3.0a3.dist-info/LICENSE
geneweaver_boolean_algebra-0.3.0a3.dist-info/METADATA
geneweaver_boolean_algebra-0.3.0a3.dist-info/WHEEL
geneweaver_boolean_algebra-0.3.0a3.dist-info/entry_points.txt
geneweaver_boolean_algebra-0.3.0a3.dist-info/RECORD
