Metadata-Version: 2.3
Name: geneweaver-boolean-algebra
Version: 0.3.0a3
Summary: Geneweaver's Boolean Algebra Tool
License: Apache-2.0
Author: Alexander Berger
Author-email: alexander.berger@jax.org
Requires-Python: >=3.10,<4.0
Classifier: License :: OSI Approved :: Apache Software License
Classifier: Programming Language :: Python :: 3
Classifier: Programming Language :: Python :: 3.10
Classifier: Programming Language :: Python :: 3.11
Classifier: Programming Language :: Python :: 3.12
Classifier: Programming Language :: Python :: 3.13
Requires-Dist: geneweaver-core (>=0.9.1,<1.0)
Requires-Dist: geneweaver-tools (>=0.0.4,<1.0)
Requires-Dist: jupyter (>=1.0.0,<2.0.0)
Requires-Dist: scipy (>=1.14.1,<2.0.0)
Project-URL: Homepage, https://bergsalex.github.io/geneweaver-docs/
Project-URL: Repository, https://github.com/bergsalex/geneweaver-boolean-algebra
